sdk_temp_1207/dynbatch/__init__.py
sdk_temp_1207/dynbatch/base.py
sdk_temp_1207/dynbatch/batch.py
sdk_temp_1207/rlog/__init__.py
sdk_temp_1207/rlog/eventhub.py
sdk_temp_1207/rlog/log.py
sdk_temp_1207/rlog/logimp.py
sdk_temp_1207-0.1.0.dist-info/WHEEL
sdk_temp_1207-0.1.0.dist-info/METADATA
sdk_temp_1207-0.1.0.dist-info/RECORD
